reprostim/__about__.py
reprostim/__init__.py
reprostim/__main__.py
reprostim/_version.py
reprostim/assets/img/nosignal.png
reprostim/audio/__init__.py
reprostim/audio/audiocodes.py
reprostim/capture/__init__.py
reprostim/capture/nosignal.py
reprostim/cli/__init__.py
reprostim/cli/cmd_detect_noscreen.py
reprostim/cli/cmd_echo.py
reprostim/cli/cmd_list_displays.py
reprostim/cli/cmd_monitor_displays.py
reprostim/cli/cmd_qr_parse.py
reprostim/cli/cmd_timesync_stimuli.py
reprostim/cli/cmd_video_audit.py
reprostim/cli/entrypoint.py
reprostim/qr/__init__.py
reprostim/qr/disp_mon.py
reprostim/qr/psychopy.py
reprostim/qr/qr_parse.py
reprostim/qr/timesync_stimuli.py
reprostim/qr/video_audit.py
reprostim-0.7.23.dist-info/METADATA
reprostim-0.7.23.dist-info/WHEEL
reprostim-0.7.23.dist-info/entry_points.txt
reprostim-0.7.23.dist-info/licenses/LICENSES/MIT.txt
reprostim-0.7.23.dist-info/RECORD
