Metadata-Version: 2.4
Name: reprostim
Version: 0.7.23
Summary: ReproStim is a video capture and recording suite for neuroimaging and psychology experiments.
Project-URL: Documentation, https://github.com/ReproNim/reprostim
Project-URL: Issues, https://github.com/ReproNim/reprostim/issues
Project-URL: Source, https://github.com/ReproNim/reprostim
Author-email: ReproNim Team <info@repronim.org>, Yaroslav Halchenko <yoh@dartmouth.edu>, Andy Connolly <andrew.c.connolly@dartmouth.edu>, Horea Christian <chr@chymera.eu>, Vadim Melnik <vmelnik@docsultant.com>
License-Expression: MIT
License-File: LICENSES/MIT.txt
Keywords: ReproStim,reprostim-screncapture,reprostim-videocapture
Classifier: Development Status :: 3 - Alpha
Classifier: Programming Language :: Python
Classifier: Programming Language :: Python :: 3.10
Classifier: Programming Language :: Python :: Implementation :: CPython
Classifier: Programming Language :: Python :: Implementation :: PyPy
Requires-Dist: click-didyoumean>=0.3.1
Requires-Dist: click>=8.1.7
Requires-Dist: filelock>=3.16.0
Requires-Dist: numpy>=1.26.4
Requires-Dist: opencv-python>=4.9.0.80
Requires-Dist: pydantic>=2.7.1
Requires-Dist: pyzbar>=0.1.9
Requires-Dist: qrcode>=8.0
Provides-Extra: all
Requires-Dist: psychopy; extra == 'all'
Requires-Dist: psychopy-sounddevice; extra == 'all'
Requires-Dist: pyaudio>=0.2.14; extra == 'all'
Requires-Dist: pydub>=0.25.1; extra == 'all'
Requires-Dist: pygame>=2.6.1; extra == 'all'
Requires-Dist: pyglet>=1.5.27; extra == 'all'
Requires-Dist: pyobjc-core>=10.3.2; (sys_platform == 'darwin') and extra == 'all'
Requires-Dist: pyobjc-framework-quartz>=10.3.2; (sys_platform == 'darwin') and extra == 'all'
Requires-Dist: python-xlib>=0.33; (sys_platform == 'linux') and extra == 'all'
Requires-Dist: pyudev>=0.23.0; (sys_platform == 'linux') and extra == 'all'
Requires-Dist: reedsolo>=1.7.0; extra == 'all'
Requires-Dist: scipy>=1.14.1; extra == 'all'
Requires-Dist: sounddevice>=0.5.1; extra == 'all'
Provides-Extra: audio
Requires-Dist: pyaudio>=0.2.14; extra == 'audio'
Requires-Dist: pydub>=0.25.1; extra == 'audio'
Requires-Dist: reedsolo>=1.7.0; extra == 'audio'
Requires-Dist: scipy>=1.14.1; extra == 'audio'
Requires-Dist: sounddevice>=0.5.1; extra == 'audio'
Provides-Extra: disp-mon
Requires-Dist: pygame>=2.6.1; extra == 'disp-mon'
Requires-Dist: pyglet>=1.5.27; extra == 'disp-mon'
Requires-Dist: pyobjc-core>=10.3.2; (sys_platform == 'darwin') and extra == 'disp-mon'
Requires-Dist: pyobjc-framework-quartz>=10.3.2; (sys_platform == 'darwin') and extra == 'disp-mon'
Requires-Dist: python-xlib>=0.33; (sys_platform == 'linux') and extra == 'disp-mon'
Requires-Dist: pyudev>=0.23.0; (sys_platform == 'linux') and extra == 'disp-mon'
Provides-Extra: docs
Requires-Dist: pydub>=0.25.1; extra == 'docs'
Requires-Dist: pygame>=2.6.1; extra == 'docs'
Requires-Dist: pyglet>=1.5.27; extra == 'docs'
Requires-Dist: pyobjc-core>=10.3.2; (sys_platform == 'darwin') and extra == 'docs'
Requires-Dist: pyobjc-framework-quartz>=10.3.2; (sys_platform == 'darwin') and extra == 'docs'
Requires-Dist: python-xlib>=0.33; (sys_platform == 'linux') and extra == 'docs'
Requires-Dist: pyudev>=0.23.0; (sys_platform == 'linux') and extra == 'docs'
Requires-Dist: reedsolo>=1.7.0; extra == 'docs'
Requires-Dist: scipy>=1.14.1; extra == 'docs'
Requires-Dist: sounddevice>=0.5.1; extra == 'docs'
Provides-Extra: psychopy
Requires-Dist: psychopy; extra == 'psychopy'
Requires-Dist: psychopy-sounddevice; extra == 'psychopy'
